pyfonts/__init__.py
pyfonts/cache.py
pyfonts/google.py
pyfonts/is_valid.py
pyfonts/main.py
pyfonts/preview_font.py
pyfonts-1.1.3.dist-info/licenses/LICENSE
pyfonts-1.1.3.dist-info/METADATA
pyfonts-1.1.3.dist-info/WHEEL
pyfonts-1.1.3.dist-info/top_level.txt
pyfonts-1.1.3.dist-info/RECORD
