Metadata-Version: 2.4
Name: pyfonts
Version: 1.1.3
Summary: A simple and reproducible way of using fonts in matplotlib
Author-email: Joseph Barbier <joseph.barbierdarnal@gmail.com>
License-Expression: MIT
Project-URL: Homepage, https://y-sunflower.github.io/pyfonts/
Project-URL: Issues, https://github.com/y-sunflower/pyfonts/issues
Project-URL: Documentation, https://y-sunflower.github.io/pyfonts/
Project-URL: Repository, https://github.com/y-sunflower/pyfonts
Keywords: matplotlib,font,reproducibility,google
Classifier: Programming Language :: Python :: 3
Classifier: Operating System :: OS Independent
Classifier: Framework :: Matplotlib
Classifier: Development Status :: 5 - Production/Stable
Requires-Python: >=3.9
License-File: LICENSE
Requires-Dist: matplotlib
Requires-Dist: requests
Dynamic: license-file
